{"activity_name": "Users", "request_id": 3, "is_keyboard_deployed": false, "activity": {"added_fragments": ["1"], "active_fragments": ["1"], "root": {"class": "RelativeLayout", "visibility": "", "children": [{"class": "ImageView", "visibility": "visible", "bounds": [100, 101, 151, 122]}, {"class": "ImageView", "visibility": "visible", "bounds": [346, 59, 368, 75]}, {"class": "ImageView", "visibility": "visible", "bounds": [74, 12, 125, 34]}, {"class": "ImageView", "visibility": "visible", "bounds": [375, 2, 396, 176]}, {"class": "TextView", "visibility": "visible", "text": "News Sections", "bounds": [80, 61, 180, 73]}, {"class": "TextView", "visibility": "visible", "text": "Davos 2019", "bounds": [106, 150, 184, 161]}], "bounds": [0, 0, 1440, 2560]}}}