{"activity_name": "Users", "request_id": 3, "is_keyboard_deployed": false, "activity": {"added_fragments": ["1"], "active_fragments": ["1"], "root": {"class": "RelativeLayout", "visibility": "", "children": [{"class": "RelativeLayout", "visibility": "", "children": [{"class": "ImageView", "visibility": "visible", "bounds": [13, 13, 39, 39]}], "bounds": [818, 1831, 870, 1883]}, {"class": "RelativeLayout", "visibility": "", "children": [{"class": "ImageView", "visibility": "visible", "bounds": [14, 14, 44, 44]}], "bounds": [511, 1828, 569, 1886]}, {"class": "RelativeLayout", "visibility": "", "children": [{"class": "ImageView", "visibility": "visible", "bounds": [22, 20, 37, 38]}], "bounds": [211, 1828, 262, 1886]}, {"class": "RelativeLayout", "visibility": "", "children": [{"class": "ImageView", "visibility": "visible", "bounds": [20, 48, 45, 56]}], "bounds": [143, 1679, 207, 1743]}, {"class": "RelativeLayout", "visibility": "", "children": [{"class": "ImageView", "visibility": "visible", "bounds": [24, 13, 36, 26]}, {"class": "ImageView", "visibility": "visible", "bounds": [44, 12, 54, 22]}], "bounds": [874, 1677, 938, 1745]}, {"class": "RelativeLayout", "visibility": "", "children": [{"class": "ImageView", "visibility": "visible", "bounds": [338, 320, 348, 332]}], "bounds": [0, 168, 1080, 509]}, {"class": "RelativeLayout", "visibility": "", "children": [{"class": "ImageView", "visibility": "visible", "bounds": [13, 15, 27, 26]}], "bounds": [406, 99, 637, 139]}, {"class": "ImageView", "visibility": "visible", "bounds": [0, 1789, 1080, 1798]}, {"class": "ImageView", "visibility": "visible", "bounds": [881, 1749, 931, 1781]}, {"class": "ImageView", "visibility": "visible", "bounds": [348, 1748, 490, 1787]}, {"class": "ImageView", "visibility": "visible", "bounds": [621, 1747, 705, 1781]}, {"class": "ImageView", "visibility": "visible", "bounds": [116, 1747, 233, 1781]}, {"class": "ImageView", "visibility": "visible", "bounds": [389, 1681, 449, 1741]}, {"class": "ImageView", "visibility": "visible", "bounds": [634, 1675, 716, 1743]}, {"class": "ImageView", "visibility": "visible", "bounds": [263, 1255, 318, 1424]}, {"class": "ImageView", "visibility": "visible", "bounds": [37, 1151, 1043, 1665]}, {"class": "ImageView", "visibility": "visible", "bounds": [92, 1151, 414, 1553]}, {"class": "ImageView", "visibility": "visible", "bounds": [317, 1071, 535, 1136]}, {"class": "ImageView", "visibility": "visible", "bounds": [221, 936, 345, 979]}, {"class": "ImageView", "visibility": "visible", "bounds": [44, 935, 83, 977]}, {"class": "ImageView", "visibility": "visible", "bounds": [1064, 720, 1080, 752]}, {"class": "ImageView", "visibility": "visible", "bounds": [439, 711, 501, 752]}, {"class": "ImageView", "visibility": "visible", "bounds": [222, 711, 435, 752]}, {"class": "ImageView", "visibility": "visible", "bounds": [78, 711, 147, 752]}, {"class": "ImageView", "visibility": "visible", "bounds": [1067, 668, 1080, 700]}, {"class": "ImageView", "visibility": "visible", "bounds": [77, 660, 230, 700]}, {"class": "ImageView", "visibility": "visible", "bounds": [574, 659, 708, 708]}, {"class": "ImageView", "visibility": "visible", "bounds": [234, 659, 344, 700]}, {"class": "ImageView", "visibility": "visible", "bounds": [839, 437, 889, 488]}, {"class": "ImageView", "visibility": "visible", "bounds": [937, 428, 1074, 483]}, {"class": "ImageView", "visibility": "visible", "bounds": [665, 383, 694, 403]}, {"class": "ImageView", "visibility": "visible", "bounds": [481, 381, 590, 405]}, {"class": "ImageView", "visibility": "visible", "bounds": [970, 327, 1026, 444]}, {"class": "ImageView", "visibility": "visible", "bounds": [1067, 283, 1080, 297]}, {"class": "ImageView", "visibility": "visible", "bounds": [853, 279, 909, 300]}, {"class": "ImageView", "visibility": "visible", "bounds": [813, 271, 841, 299]}, {"class": "ImageView", "visibility": "visible", "bounds": [897, 236, 921, 261]}, {"class": "ImageView", "visibility": "visible", "bounds": [977, 235, 1006, 266]}, {"class": "ImageView", "visibility": "visible", "bounds": [1018, 216, 1030, 239]}, {"class": "ImageView", "visibility": "visible", "bounds": [830, 214, 865, 265]}, {"class": "ImageView", "visibility": "visible", "bounds": [927, 184, 995, 326]}, {"class": "ImageView", "visibility": "visible", "bounds": [66, 148, 143, 164]}, {"class": "ImageView", "visibility": "visible", "bounds": [992, 127, 1040, 141]}, {"class": "ImageView", "visibility": "visible", "bounds": [992, 112, 1040, 126]}, {"class": "ImageView", "visibility": "visible", "bounds": [868, 98, 981, 139]}, {"class": "ImageView", "visibility": "visible", "bounds": [698, 98, 807, 139]}, {"class": "ImageView", "visibility": "visible", "bounds": [240, 98, 345, 139]}, {"class": "ImageView", "visibility": "visible", "bounds": [100, 97, 193, 142]}, {"class": "ImageView", "visibility": "visible", "bounds": [16, 97, 96, 142]}, {"class": "ImageView", "visibility": "visible", "bounds": [992, 87, 1051, 111]}, {"class": "ImageView", "visibility": "visible", "bounds": [872, 9, 926, 54]}, {"class": "ImageView", "visibility": "visible", "bounds": [939, 8, 971, 54]}, {"class": "ImageView", "visibility": "visible", "bounds": [23, 8, 72, 53]}, {"class": "TextView", "visibility": "visible", "text": "3:40", "bounds": [988, 19, 1057, 47]}, {"class": "TextView", "visibility": "visible", "text": "@ ABC News", "bounds": [843, 451, 1069, 493]}, {"class": "TextView", "visibility": "visible", "text": "Most Shared", "bounds": [94, 546, 272, 571]}, {"class": "TextView", "visibility": "visible", "text": "Most Shared", "bounds": [856, 545, 1033, 569]}, {"class": "TextView", "visibility": "visible", "text": "FDA approval of the Covid-19", "bounds": [84, 613, 632, 654]}, {"class": "TextView", "visibility": "visible", "text": "School distri", "bounds": [844, 611, 1079, 644]}, {"class": "TextView", "visibility": "visible", "text": "vaccine could mean more people", "bounds": [81, 672, 704, 713]}, {"class": "TextView", "visibility": "visible", "text": "crackdown,", "bounds": [844, 663, 1057, 702]}, {"class": "TextView", "visibility": "visible", "text": "will get vaccinated for an...", "bounds": [82, 724, 587, 761]}, {"class": "TextView", "visibility": "visible", "text": "students to", "bounds": [844, 715, 1056, 748]}, {"class": "TextView", "visibility": "visible", "text": "Fairfax County", "bounds": [105, 939, 340, 967]}, {"class": "TextView", "visibility": "visible", "text": "Some Fairfax County parents petition", "bounds": [44, 1009, 1032, 1063]}, {"class": "TextView", "visibility": "visible", "text": "for virtual learning", "bounds": [43, 1075, 530, 1120]}], "bounds": [0, 0, 1440, 2560]}}}