{"activity_name": "Users", "request_id": 3, "is_keyboard_deployed": false, "activity": {"added_fragments": ["1"], "active_fragments": ["1"], "root": {"class": "RelativeLayout", "visibility": "", "children": [{"class": "RelativeLayout", "visibility": "", "children": [{"class": "ImageView", "visibility": "visible", "bounds": [13, 13, 39, 39]}], "bounds": [818, 1831, 870, 1883]}, {"class": "RelativeLayout", "visibility": "", "children": [{"class": "ImageView", "visibility": "visible", "bounds": [14, 14, 44, 44]}], "bounds": [511, 1828, 569, 1886]}, {"class": "RelativeLayout", "visibility": "", "children": [{"class": "ImageView", "visibility": "visible", "bounds": [22, 20, 37, 38]}], "bounds": [211, 1828, 262, 1886]}, {"class": "RelativeLayout", "visibility": "", "children": [{"class": "ImageView", "visibility": "visible", "bounds": [19, 12, 51, 33]}], "bounds": [744, 1158, 814, 1203]}, {"class": "RelativeLayout", "visibility": "", "children": [{"class": "ImageView", "visibility": "visible", "bounds": [11, 11, 39, 31]}], "bounds": [275, 1155, 326, 1206]}, {"class": "RelativeLayout", "visibility": "", "children": [{"class": "ImageView", "visibility": "visible", "bounds": [28, 20, 51, 41]}], "bounds": [31, 1153, 96, 1206]}, {"class": "RelativeLayout", "visibility": "", "children": [{"class": "ImageView", "visibility": "visible", "bounds": [19, 11, 51, 32]}], "bounds": [744, 609, 814, 654]}, {"class": "RelativeLayout", "visibility": "", "children": [{"class": "ImageView", "visibility": "visible", "bounds": [12, 11, 40, 31]}], "bounds": [275, 606, 326, 657]}, {"class": "ImageView", "visibility": "visible", "bounds": [0, 1604, 1080, 1799]}, {"class": "ImageView", "visibility": "visible", "bounds": [781, 1529, 882, 1576]}, {"class": "ImageView", "visibility": "visible", "bounds": [890, 1523, 1035, 1576]}, {"class": "ImageView", "visibility": "visible", "bounds": [598, 1521, 773, 1571]}, {"class": "ImageView", "visibility": "visible", "bounds": [145, 1520, 189, 1566]}, {"class": "ImageView", "visibility": "visible", "bounds": [533, 1519, 592, 1576]}, {"class": "ImageView", "visibility": "visible", "bounds": [336, 1519, 524, 1566]}, {"class": "ImageView", "visibility": "visible", "bounds": [197, 1519, 331, 1565]}, {"class": "ImageView", "visibility": "visible", "bounds": [30, 1519, 139, 1565]}, {"class": "ImageView", "visibility": "visible", "bounds": [601, 1459, 654, 1501]}, {"class": "ImageView", "visibility": "visible", "bounds": [164, 1457, 235, 1502]}, {"class": "ImageView", "visibility": "visible", "bounds": [799, 1455, 968, 1502]}, {"class": "ImageView", "visibility": "visible", "bounds": [660, 1455, 791, 1513]}, {"class": "ImageView", "visibility": "visible", "bounds": [498, 1455, 595, 1501]}, {"class": "ImageView", "visibility": "visible", "bounds": [242, 1455, 490, 1502]}, {"class": "ImageView", "visibility": "visible", "bounds": [29, 1455, 156, 1502]}, {"class": "ImageView", "visibility": "visible", "bounds": [856, 1365, 896, 1405]}, {"class": "ImageView", "visibility": "visible", "bounds": [512, 1157, 573, 1204]}, {"class": "ImageView", "visibility": "visible", "bounds": [1007, 1155, 1026, 1206]}, {"class": "ImageView", "visibility": "visible", "bounds": [29, 1074, 78, 1103]}, {"class": "ImageView", "visibility": "visible", "bounds": [84, 1071, 127, 1103]}, {"class": "ImageView", "visibility": "visible", "bounds": [484, 991, 652, 1049]}, {"class": "ImageView", "visibility": "visible", "bounds": [856, 826, 896, 866]}, {"class": "ImageView", "visibility": "visible", "bounds": [29, 791, 138, 900]}, {"class": "ImageView", "visibility": "visible", "bounds": [512, 608, 573, 655]}, {"class": "ImageView", "visibility": "visible", "bounds": [1007, 606, 1026, 657]}, {"class": "ImageView", "visibility": "visible", "bounds": [29, 525, 78, 554]}, {"class": "ImageView", "visibility": "visible", "bounds": [83, 522, 127, 554]}, {"class": "ImageView", "visibility": "visible", "bounds": [0, 174, 1080, 502]}, {"class": "ImageView", "visibility": "visible", "bounds": [661, 102, 804, 139]}, {"class": "ImageView", "visibility": "visible", "bounds": [139, 102, 239, 138]}, {"class": "ImageView", "visibility": "visible", "bounds": [479, 101, 604, 139]}, {"class": "ImageView", "visibility": "visible", "bounds": [296, 101, 420, 138]}, {"class": "ImageView", "visibility": "visible", "bounds": [28, 101, 78, 139]}, {"class": "ImageView", "visibility": "visible", "bounds": [872, 9, 926, 54]}, {"class": "ImageView", "visibility": "visible", "bounds": [939, 8, 971, 54]}, {"class": "TextView", "visibility": "visible", "text": "an", "bounds": [33, 13, 129, 50]}, {"class": "TextView", "visibility": "visible", "text": "4:49", "bounds": [987, 19, 1057, 46]}, {"class": "TextView", "visibility": "visible", "text": "Topics", "bounds": [868, 107, 974, 142]}, {"class": "TextView", "visibility": "visible", "text": "Gr", "bounds": [1042, 107, 1078, 134]}, {"class": "TextView", "visibility": "visible", "text": "10", "bounds": [36, 608, 89, 652]}, {"class": "TextView", "visibility": "visible", "text": "Business Wire INDIA @", "bounds": [160, 831, 567, 872]}, {"class": "TextView", "visibility": "visible", "text": "Follow", "bounds": [908, 833, 1016, 860]}, {"class": "TextView", "visibility": "visible", "text": "Manage Working Capital With an Instant", "bounds": [35, 933, 922, 982]}, {"class": "TextView", "visibility": "visible", "text": "Business Loan From Ziploan", "bounds": [35, 995, 648, 1031]}, {"class": "TextView", "visibility": "visible", "text": "FINANCIAL EXPRESS", "bounds": [32, 1366, 334, 1403]}, {"class": "TextView", "visibility": "visible", "text": "Follow", "bounds": [908, 1372, 1016, 1400]}], "bounds": [0, 0, 1440, 2560]}}}