{"activity_name": "Users", "request_id": 3, "is_keyboard_deployed": false, "activity": {"added_fragments": ["1"], "active_fragments": ["1"], "root": {"class": "RelativeLayout", "visibility": "", "children": [{"class": "ImageView", "visibility": "visible", "bounds": [0, 229, 1080, 238]}, {"class": "ImageView", "visibility": "visible", "bounds": [0, 131, 1080, 143]}, {"class": "ImageView", "visibility": "visible", "bounds": [12, 1, 46, 35]}, {"class": "RelativeLayout", "visibility": "", "children": [{"class": "ImageView", "visibility": "visible", "bounds": [39, 17, 59, 53]}, {"class": "ImageView", "visibility": "visible", "bounds": [11, 11, 45, 59]}], "bounds": [19, 49, 89, 119]}, {"class": "TextView", "visibility": "visible", "text": "6:10", "bounds": [1027, 11, 1067, 26]}, {"class": "TextView", "visibility": "visible", "text": "Help", "bounds": [974, 72, 1056, 109]}, {"class": "TextView", "visibility": "visible", "text": "Frequently asked questions", "bounds": [25, 177, 316, 200]}, {"class": "TextView", "visibility": "visible", "text": "Contact us", "bounds": [24, 281, 151, 302]}, {"class": "TextView", "visibility": "visible", "text": "Report an issue", "bounds": [25, 372, 187, 394]}, {"class": "TextView", "visibility": "visible", "text": "Subscriptions, payment and billing issues", "bounds": [24, 468, 465, 491]}, {"class": "TextView", "visibility": "visible", "text": "Membership payment, billing or help issues", "bounds": [25, 564, 492, 587]}, {"class": "TextView", "visibility": "visible", "text": "Comment or query about an article", "bounds": [24, 659, 395, 677]}, {"class": "TextView", "visibility": "visible", "text": "Query about moderation of comments", "bounds": [24, 756, 432, 778]}, {"class": "TextView", "visibility": "visible", "text": "Send feedback", "bounds": [24, 850, 181, 868]}], "bounds": [0, 0, 1440, 2560]}}}