{"activity_name": "Users", "request_id": 3, "is_keyboard_deployed": false, "activity": {"added_fragments": ["1"], "active_fragments": ["1"], "root": {"class": "RelativeLayout", "visibility": "", "children": [{"class": "RelativeLayout", "visibility": "", "children": [{"class": "ImageView", "visibility": "visible", "bounds": [13, 13, 39, 39]}], "bounds": [818, 1831, 870, 1883]}, {"class": "RelativeLayout", "visibility": "", "children": [{"class": "ImageView", "visibility": "visible", "bounds": [14, 14, 44, 44]}], "bounds": [511, 1828, 569, 1886]}, {"class": "RelativeLayout", "visibility": "", "children": [{"class": "ImageView", "visibility": "visible", "bounds": [22, 20, 37, 38]}], "bounds": [211, 1828, 262, 1886]}, {"class": "RelativeLayout", "visibility": "", "children": [{"class": "ImageView", "visibility": "visible", "bounds": [183, 29, 191, 42]}], "bounds": [638, 402, 860, 459]}, {"class": "RelativeLayout", "visibility": "", "children": [{"class": "ImageView", "visibility": "visible", "bounds": [77, 29, 93, 41]}], "bounds": [355, 402, 487, 459]}, {"class": "RelativeLayout", "visibility": "", "children": [{"class": "ImageView", "visibility": "visible", "bounds": [23, 25, 41, 42]}], "bounds": [733, 105, 797, 166]}, {"class": "ImageView", "visibility": "visible", "bounds": [0, 1775, 1080, 1799]}, {"class": "ImageView", "visibility": "visible", "bounds": [685, 1723, 903, 1770]}, {"class": "ImageView", "visibility": "visible", "bounds": [34, 1483, 1046, 1496]}, {"class": "ImageView", "visibility": "visible", "bounds": [637, 1433, 769, 1464]}, {"class": "ImageView", "visibility": "visible", "bounds": [37, 1431, 218, 1471]}, {"class": "ImageView", "visibility": "visible", "bounds": [1058, 1125, 1069, 1136]}, {"class": "ImageView", "visibility": "visible", "bounds": [988, 1089, 1046, 1228]}, {"class": "ImageView", "visibility": "visible", "bounds": [1053, 1086, 1080, 1097]}, {"class": "ImageView", "visibility": "visible", "bounds": [147, 664, 167, 684]}, {"class": "ImageView", "visibility": "visible", "bounds": [0, 639, 1080, 1245]}, {"class": "ImageView", "visibility": "visible", "bounds": [0, 563, 1080, 573]}, {"class": "ImageView", "visibility": "visible", "bounds": [289, 481, 448, 539]}, {"class": "ImageView", "visibility": "visible", "bounds": [39, 481, 279, 552]}, {"class": "ImageView", "visibility": "visible", "bounds": [500, 415, 629, 459]}, {"class": "ImageView", "visibility": "visible", "bounds": [870, 402, 960, 459]}, {"class": "ImageView", "visibility": "visible", "bounds": [39, 402, 217, 459]}, {"class": "ImageView", "visibility": "visible", "bounds": [229, 401, 345, 459]}, {"class": "ImageView", "visibility": "visible", "bounds": [423, 335, 560, 392]}, {"class": "ImageView", "visibility": "visible", "bounds": [734, 322, 916, 379]}, {"class": "ImageView", "visibility": "visible", "bounds": [573, 322, 720, 388]}, {"class": "ImageView", "visibility": "visible", "bounds": [231, 322, 409, 379]}, {"class": "ImageView", "visibility": "visible", "bounds": [39, 322, 215, 379]}, {"class": "ImageView", "visibility": "visible", "bounds": [499, 257, 512, 270]}, {"class": "ImageView", "visibility": "visible", "bounds": [179, 257, 192, 270]}, {"class": "ImageView", "visibility": "visible", "bounds": [813, 248, 899, 281]}, {"class": "ImageView", "visibility": "visible", "bounds": [774, 248, 811, 280]}, {"class": "ImageView", "visibility": "visible", "bounds": [694, 248, 772, 281]}, {"class": "ImageView", "visibility": "visible", "bounds": [593, 248, 693, 289]}, {"class": "ImageView", "visibility": "visible", "bounds": [522, 248, 592, 281]}, {"class": "ImageView", "visibility": "visible", "bounds": [902, 247, 952, 280]}, {"class": "ImageView", "visibility": "visible", "bounds": [217, 246, 478, 280]}, {"class": "ImageView", "visibility": "visible", "bounds": [36, 246, 158, 280]}, {"class": "ImageView", "visibility": "visible", "bounds": [0, 206, 1080, 215]}, {"class": "ImageView", "visibility": "visible", "bounds": [49, 112, 99, 161]}, {"class": "ImageView", "visibility": "visible", "bounds": [1003, 107, 1025, 169]}, {"class": "ImageView", "visibility": "visible", "bounds": [863, 107, 918, 165]}, {"class": "ImageView", "visibility": "visible", "bounds": [983, 15, 1062, 51]}, {"class": "ImageView", "visibility": "visible", "bounds": [872, 9, 926, 54]}, {"class": "ImageView", "visibility": "visible", "bounds": [939, 8, 971, 54]}, {"class": "ImageView", "visibility": "visible", "bounds": [23, 8, 72, 53]}, {"class": "TextView", "visibility": "visible", "text": "FILE PHOTO: Members of South Korea and U.S. Special forces take", "bounds": [42, 1267, 969, 1298]}, {"class": "TextView", "visibility": "visible", "text": "partin a joint military exercise conducted by South Korean and U.S.", "bounds": [42, 1311, 991, 1342]}, {"class": "TextView", "visibility": "visible", "text": "special forces troops at Gunsan Air Force base in Gunsan, South Korea,", "bounds": [40, 1353, 1036, 1384]}, {"class": "TextView", "visibility": "visible", "text": "November 14, 2019. Photo taken November 14, 2019. Capt. David J.", "bounds": [42, 1395, 998, 1424]}, {"class": "TextView", "visibility": "visible", "text": "Air Force/DVIDS/Handout via", "bounds": [224, 1435, 630, 1465]}, {"class": "TextView", "visibility": "visible", "text": "By Hyonhee Shin and Josh Smith | SEOUL", "bounds": [42, 1558, 709, 1597]}, {"class": "TextView", "visibility": "visible", "text": "South Korea and the United States will face even greater", "bounds": [41, 1679, 1021, 1709]}, {"class": "TextView", "visibility": "visible", "text": "security threats for going ahead with", "bounds": [40, 1728, 676, 1766]}], "bounds": [0, 0, 1440, 2560]}}}