{"activity_name": "Users", "request_id": 3, "is_keyboard_deployed": false, "activity": {"added_fragments": ["1"], "active_fragments": ["1"], "root": {"class": "RelativeLayout", "visibility": "", "children": [{"class": "RelativeLayout", "visibility": "", "children": [{"class": "ImageView", "visibility": "visible", "bounds": [13, 13, 39, 39]}], "bounds": [818, 1831, 870, 1883]}, {"class": "RelativeLayout", "visibility": "", "children": [{"class": "ImageView", "visibility": "visible", "bounds": [14, 14, 44, 44]}], "bounds": [511, 1828, 569, 1886]}, {"class": "RelativeLayout", "visibility": "", "children": [{"class": "ImageView", "visibility": "visible", "bounds": [22, 20, 37, 38]}], "bounds": [211, 1828, 262, 1886]}, {"class": "RelativeLayout", "visibility": "", "children": [{"class": "ImageView", "visibility": "visible", "bounds": [20, 31, 32, 40]}], "bounds": [51, 544, 97, 595]}, {"class": "RelativeLayout", "visibility": "", "children": [{"class": "ImageView", "visibility": "visible", "bounds": [13, 18, 48, 48]}], "bounds": [43, 116, 104, 177]}, {"class": "RelativeLayout", "visibility": "", "children": [{"class": "ImageView", "visibility": "visible", "bounds": [14, 14, 37, 37]}], "bounds": [860, 105, 921, 166]}, {"class": "RelativeLayout", "visibility": "", "children": [{"class": "ImageView", "visibility": "visible", "bounds": [8, 17, 31, 39]}], "bounds": [154, 8, 193, 55]}, {"class": "RelativeLayout", "visibility": "", "children": [{"class": "ImageView", "visibility": "visible", "bounds": [23, 24, 38, 31]}], "bounds": [21, 8, 75, 55]}, {"class": "ImageView", "visibility": "visible", "bounds": [920, 1043, 1013, 1080]}, {"class": "ImageView", "visibility": "visible", "bounds": [812, 1030, 910, 1080]}, {"class": "ImageView", "visibility": "visible", "bounds": [356, 562, 412, 594]}, {"class": "ImageView", "visibility": "visible", "bounds": [420, 554, 508, 601]}, {"class": "ImageView", "visibility": "visible", "bounds": [187, 554, 265, 593]}, {"class": "ImageView", "visibility": "visible", "bounds": [270, 552, 350, 594]}, {"class": "ImageView", "visibility": "visible", "bounds": [187, 426, 362, 475]}, {"class": "ImageView", "visibility": "visible", "bounds": [50, 418, 97, 469]}, {"class": "ImageView", "visibility": "visible", "bounds": [290, 257, 331, 296]}, {"class": "ImageView", "visibility": "visible", "bounds": [187, 255, 282, 304]}, {"class": "ImageView", "visibility": "visible", "bounds": [43, 247, 104, 298]}, {"class": "ImageView", "visibility": "visible", "bounds": [188, 131, 313, 170]}, {"class": "ImageView", "visibility": "visible", "bounds": [981, 102, 1047, 166]}, {"class": "ImageView", "visibility": "visible", "bounds": [213, 12, 260, 51]}, {"class": "ImageView", "visibility": "visible", "bounds": [87, 8, 133, 55]}, {"class": "ImageView", "visibility": "visible", "bounds": [0, 0, 1080, 1799]}], "bounds": [0, 0, 1440, 2560]}}}