{"activity_name": "Users", "request_id": 3, "is_keyboard_deployed": false, "activity": {"added_fragments": ["1"], "active_fragments": ["1"], "root": {"class": "RelativeLayout", "visibility": "", "children": [{"class": "RelativeLayout", "visibility": "", "children": [{"class": "ImageView", "visibility": "visible", "bounds": [13, 13, 39, 39]}], "bounds": [818, 1831, 870, 1883]}, {"class": "RelativeLayout", "visibility": "", "children": [{"class": "ImageView", "visibility": "visible", "bounds": [14, 14, 44, 44]}], "bounds": [511, 1828, 569, 1886]}, {"class": "RelativeLayout", "visibility": "", "children": [{"class": "ImageView", "visibility": "visible", "bounds": [22, 20, 37, 38]}], "bounds": [211, 1828, 262, 1886]}, {"class": "RelativeLayout", "visibility": "", "children": [{"class": "ImageView", "visibility": "visible", "bounds": [24, 27, 42, 45]}], "bounds": [724, 1651, 790, 1717]}, {"class": "RelativeLayout", "visibility": "", "children": [{"class": "ImageView", "visibility": "visible", "bounds": [14, 11, 59, 59]}], "bounds": [72, 1651, 146, 1718]}, {"class": "RelativeLayout", "visibility": "", "children": [{"class": "ImageView", "visibility": "visible", "bounds": [17, 26, 99, 110]}], "bounds": [614, 859, 730, 986]}, {"class": "RelativeLayout", "visibility": "", "children": [{"class": "ImageView", "visibility": "visible", "bounds": [11, 11, 308, 222]}], "bounds": [376, 604, 695, 837]}, {"class": "RelativeLayout", "visibility": "", "children": [{"class": "ImageView", "visibility": "visible", "bounds": [115, 8, 380, 12]}], "bounds": [0, 321, 1080, 341]}, {"class": "RelativeLayout", "visibility": "", "children": [{"class": "ImageView", "visibility": "visible", "bounds": [13, 13, 31, 31]}], "bounds": [184, 114, 235, 165]}, {"class": "RelativeLayout", "visibility": "", "children": [{"class": "ImageView", "visibility": "visible", "bounds": [17, 18, 36, 45]}], "bounds": [957, 101, 1010, 164]}, {"class": "RelativeLayout", "visibility": "", "children": [{"class": "ImageView", "visibility": "visible", "bounds": [53, 60, 66, 73]}, {"class": "ImageView", "visibility": "visible", "bounds": [25, 60, 39, 73]}], "bounds": [38, 91, 130, 183]}, {"class": "ImageView", "visibility": "visible", "bounds": [0, 1789, 1080, 1798]}, {"class": "ImageView", "visibility": "visible", "bounds": [938, 1736, 1008, 1764]}, {"class": "ImageView", "visibility": "visible", "bounds": [510, 1664, 574, 1703]}, {"class": "ImageView", "visibility": "visible", "bounds": [945, 1662, 1001, 1706]}, {"class": "ImageView", "visibility": "visible", "bounds": [289, 1651, 362, 1717]}, {"class": "ImageView", "visibility": "visible", "bounds": [194, 1538, 334, 1582]}, {"class": "ImageView", "visibility": "visible", "bounds": [876, 1463, 1032, 1620]}, {"class": "ImageView", "visibility": "visible", "bounds": [717, 604, 1034, 837]}, {"class": "ImageView", "visibility": "visible", "bounds": [37, 604, 354, 837]}, {"class": "ImageView", "visibility": "visible", "bounds": [37, 457, 1044, 567]}, {"class": "ImageView", "visibility": "visible", "bounds": [586, 250, 673, 285]}, {"class": "ImageView", "visibility": "visible", "bounds": [961, 249, 993, 285]}, {"class": "ImageView", "visibility": "visible", "bounds": [0, 249, 81, 285]}, {"class": "ImageView", "visibility": "visible", "bounds": [732, 248, 903, 295]}, {"class": "ImageView", "visibility": "visible", "bounds": [415, 248, 582, 294]}, {"class": "ImageView", "visibility": "visible", "bounds": [1008, 243, 1059, 294]}, {"class": "ImageView", "visibility": "visible", "bounds": [381, 117, 489, 156]}, {"class": "ImageView", "visibility": "visible", "bounds": [659, 116, 791, 152]}, {"class": "ImageView", "visibility": "visible", "bounds": [620, 116, 653, 152]}, {"class": "ImageView", "visibility": "visible", "bounds": [493, 116, 615, 152]}, {"class": "ImageView", "visibility": "visible", "bounds": [251, 116, 373, 152]}, {"class": "ImageView", "visibility": "visible", "bounds": [87, 12, 134, 51]}, {"class": "ImageView", "visibility": "visible", "bounds": [883, 9, 937, 54]}, {"class": "ImageView", "visibility": "visible", "bounds": [950, 8, 982, 54]}, {"class": "TextView", "visibility": "visible", "text": "awn", "bounds": [33, 13, 62, 50]}, {"class": "TextView", "visibility": "visible", "text": "9:16", "bounds": [999, 21, 1057, 43]}, {"class": "TextView", "visibility": "visible", "text": "Coronavirus", "bounds": [144, 253, 352, 281]}, {"class": "TextView", "visibility": "visible", "text": "As on: Sat Jul 31 2021", "bounds": [43, 395, 349, 418]}, {"class": "TextView", "visibility": "visible", "text": "All India", "bounds": [64, 492, 222, 538]}, {"class": "TextView", "visibility": "visible", "text": "v", "bounds": [1000, 504, 1015, 518]}, {"class": "TextView", "visibility": "visible", "text": "Important resources", "bounds": [45, 943, 426, 990]}, {"class": "TextView", "visibility": "visible", "text": "Vaccination Slot Locator", "bounds": [74, 1061, 472, 1089]}, {"class": "TextView", "visibility": "visible", "text": ">", "bounds": [989, 1063, 1006, 1089]}, {"class": "TextView", "visibility": "visible", "text": "COVID Vaccine Hospital List", "bounds": [76, 1182, 532, 1218]}, {"class": "TextView", "visibility": "visible", "text": ">", "bounds": [989, 1184, 1006, 1210]}, {"class": "TextView", "visibility": "visible", "text": "Lockdown FAQs", "bounds": [77, 1302, 333, 1332]}, {"class": "TextView", "visibility": "visible", "text": ">", "bounds": [989, 1305, 1007, 1330]}, {"class": "TextView", "visibility": "visible", "text": "Helpline Numbers", "bounds": [76, 1421, 364, 1457]}, {"class": "TextView", "visibility": "visible", "text": ">", "bounds": [989, 1426, 1006, 1451]}, {"class": "TextView", "visibility": "visible", "text": "Twitter Updates", "bounds": [74, 1542, 330, 1568]}, {"class": "TextView", "visibility": "visible", "text": "Home", "bounds": [75, 1735, 145, 1769]}, {"class": "TextView", "visibility": "visible", "text": "Videos", "bounds": [271, 1735, 366, 1769]}, {"class": "TextView", "visibility": "visible", "text": "Betway", "bounds": [500, 1735, 586, 1769]}, {"class": "TextView", "visibility": "visible", "text": "Follow", "bounds": [721, 1739, 796, 1759]}], "bounds": [0, 0, 1440, 2560]}}}