{"activity_name": "Users", "request_id": 3, "is_keyboard_deployed": false, "activity": {"added_fragments": ["1"], "active_fragments": ["1"], "root": {"class": "RelativeLayout", "visibility": "", "children": [{"class": "RelativeLayout", "visibility": "", "children": [{"class": "ImageView", "visibility": "visible", "bounds": [13, 13, 39, 39]}], "bounds": [818, 1831, 870, 1883]}, {"class": "RelativeLayout", "visibility": "", "children": [{"class": "ImageView", "visibility": "visible", "bounds": [14, 14, 44, 44]}], "bounds": [511, 1828, 569, 1886]}, {"class": "RelativeLayout", "visibility": "", "children": [{"class": "ImageView", "visibility": "visible", "bounds": [22, 20, 37, 38]}], "bounds": [211, 1828, 262, 1886]}, {"class": "RelativeLayout", "visibility": "", "children": [{"class": "RelativeLayout", "visibility": "", "children": [{"class": "ImageView", "visibility": "visible", "bounds": [794, 348, 850, 384]}, {"class": "ImageView", "visibility": "visible", "bounds": [563, 348, 710, 384]}, {"class": "ImageView", "visibility": "visible", "bounds": [331, 252, 450, 284]}, {"class": "ImageView", "visibility": "visible", "bounds": [170, 245, 325, 292]}, {"class": "ImageView", "visibility": "visible", "bounds": [59, 245, 95, 283]}, {"class": "ImageView", "visibility": "visible", "bounds": [99, 243, 165, 284]}, {"class": "ImageView", "visibility": "visible", "bounds": [382, 147, 519, 186]}, {"class": "ImageView", "visibility": "visible", "bounds": [524, 145, 688, 194]}, {"class": "ImageView", "visibility": "visible", "bounds": [263, 145, 330, 186]}, {"class": "ImageView", "visibility": "visible", "bounds": [57, 145, 178, 186]}, {"class": "ImageView", "visibility": "visible", "bounds": [59, 56, 181, 105]}, {"class": "ImageView", "visibility": "visible", "bounds": [191, 55, 501, 105]}, {"class": "TextView", "visibility": "visible", "text": "Would you like to receive breaking news", "bounds": [61, 158, 794, 199]}, {"class": "TextView", "visibility": "visible", "text": "notifications? You can change this anytime", "bounds": [63, 200, 855, 241]}], "bounds": [73, 405, 1007, 841]}, {"class": "ImageView", "visibility": "visible", "bounds": [737, 282, 774, 319]}], "bounds": [0, 305, 1080, 1172]}, {"class": "RelativeLayout", "visibility": "", "children": [{"class": "ImageView", "visibility": "visible", "bounds": [8, 8, 36, 30]}], "bounds": [932, 243, 989, 281]}, {"class": "ImageView", "visibility": "visible", "bounds": [252, 1768, 359, 1799]}, {"class": "ImageView", "visibility": "visible", "bounds": [75, 1752, 94, 1769]}, {"class": "ImageView", "visibility": "visible", "bounds": [791, 1728, 842, 1759]}, {"class": "ImageView", "visibility": "visible", "bounds": [430, 1722, 477, 1759]}, {"class": "ImageView", "visibility": "visible", "bounds": [628, 1721, 787, 1767]}, {"class": "ImageView", "visibility": "visible", "bounds": [481, 1719, 623, 1760]}, {"class": "ImageView", "visibility": "visible", "bounds": [846, 1718, 1000, 1760]}, {"class": "ImageView", "visibility": "visible", "bounds": [704, 1678, 761, 1718]}, {"class": "ImageView", "visibility": "visible", "bounds": [524, 1678, 618, 1718]}, {"class": "ImageView", "visibility": "visible", "bounds": [765, 1673, 812, 1710]}, {"class": "ImageView", "visibility": "visible", "bounds": [816, 1670, 989, 1718]}, {"class": "ImageView", "visibility": "visible", "bounds": [432, 1670, 518, 1711]}, {"class": "ImageView", "visibility": "visible", "bounds": [661, 1669, 699, 1711]}, {"class": "ImageView", "visibility": "visible", "bounds": [623, 1669, 656, 1710]}, {"class": "ImageView", "visibility": "visible", "bounds": [0, 1656, 1080, 1799]}, {"class": "ImageView", "visibility": "visible", "bounds": [509, 1524, 522, 1538]}, {"class": "ImageView", "visibility": "visible", "bounds": [182, 1524, 195, 1537]}, {"class": "ImageView", "visibility": "visible", "bounds": [220, 1517, 488, 1551]}, {"class": "ImageView", "visibility": "visible", "bounds": [36, 1517, 161, 1551]}, {"class": "ImageView", "visibility": "visible", "bounds": [529, 1515, 629, 1555]}, {"class": "ImageView", "visibility": "visible", "bounds": [630, 1514, 708, 1548]}, {"class": "ImageView", "visibility": "visible", "bounds": [188, 1431, 396, 1477]}, {"class": "ImageView", "visibility": "visible", "bounds": [37, 1431, 185, 1469]}, {"class": "ImageView", "visibility": "visible", "bounds": [817, 1373, 930, 1420]}, {"class": "ImageView", "visibility": "visible", "bounds": [679, 1373, 812, 1412]}, {"class": "ImageView", "visibility": "visible", "bounds": [548, 1373, 676, 1412]}, {"class": "ImageView", "visibility": "visible", "bounds": [452, 1373, 544, 1412]}, {"class": "ImageView", "visibility": "visible", "bounds": [325, 1373, 448, 1411]}, {"class": "ImageView", "visibility": "visible", "bounds": [251, 1373, 323, 1412]}, {"class": "ImageView", "visibility": "visible", "bounds": [38, 1373, 248, 1420]}, {"class": "ImageView", "visibility": "visible", "bounds": [344, 1326, 461, 1363]}, {"class": "ImageView", "visibility": "visible", "bounds": [852, 1316, 979, 1363]}, {"class": "ImageView", "visibility": "visible", "bounds": [702, 1316, 848, 1363]}, {"class": "ImageView", "visibility": "visible", "bounds": [463, 1316, 700, 1363]}, {"class": "ImageView", "visibility": "visible", "bounds": [285, 1316, 343, 1354]}, {"class": "ImageView", "visibility": "visible", "bounds": [36, 1316, 284, 1363]}, {"class": "ImageView", "visibility": "visible", "bounds": [801, 1259, 939, 1298]}, {"class": "ImageView", "visibility": "visible", "bounds": [726, 1259, 797, 1298]}, {"class": "ImageView", "visibility": "visible", "bounds": [596, 1259, 723, 1298]}, {"class": "ImageView", "visibility": "visible", "bounds": [434, 1259, 593, 1304]}, {"class": "ImageView", "visibility": "visible", "bounds": [243, 1259, 433, 1298]}, {"class": "ImageView", "visibility": "visible", "bounds": [80, 1259, 241, 1307]}, {"class": "ImageView", "visibility": "visible", "bounds": [36, 1259, 80, 1298]}, {"class": "ImageView", "visibility": "visible", "bounds": [351, 1219, 370, 1232]}, {"class": "ImageView", "visibility": "visible", "bounds": [924, 1212, 996, 1240]}, {"class": "ImageView", "visibility": "visible", "bounds": [405, 1203, 459, 1240]}, {"class": "ImageView", "visibility": "visible", "bounds": [37, 1203, 180, 1241]}, {"class": "ImageView", "visibility": "visible", "bounds": [798, 1202, 921, 1247]}, {"class": "ImageView", "visibility": "visible", "bounds": [686, 1202, 793, 1241]}, {"class": "ImageView", "visibility": "visible", "bounds": [641, 1202, 685, 1241]}, {"class": "ImageView", "visibility": "visible", "bounds": [529, 1202, 639, 1241]}, {"class": "ImageView", "visibility": "visible", "bounds": [462, 1202, 527, 1240]}, {"class": "ImageView", "visibility": "visible", "bounds": [183, 1201, 347, 1247]}, {"class": "ImageView", "visibility": "visible", "bounds": [871, 682, 892, 693]}, {"class": "ImageView", "visibility": "visible", "bounds": [1027, 667, 1072, 707]}, {"class": "ImageView", "visibility": "visible", "bounds": [914, 653, 941, 686]}, {"class": "ImageView", "visibility": "visible", "bounds": [119, 647, 155, 662]}, {"class": "ImageView", "visibility": "visible", "bounds": [316, 639, 384, 675]}, {"class": "ImageView", "visibility": "visible", "bounds": [862, 622, 881, 653]}, {"class": "ImageView", "visibility": "visible", "bounds": [403, 579, 438, 618]}, {"class": "ImageView", "visibility": "visible", "bounds": [971, 562, 993, 602]}, {"class": "ImageView", "visibility": "visible", "bounds": [72, 546, 93, 572]}, {"class": "ImageView", "visibility": "visible", "bounds": [525, 519, 541, 551]}, {"class": "ImageView", "visibility": "visible", "bounds": [17, 460, 47, 570]}, {"class": "ImageView", "visibility": "visible", "bounds": [169, 427, 211, 451]}, {"class": "ImageView", "visibility": "visible", "bounds": [943, 423, 988, 467]}, {"class": "ImageView", "visibility": "visible", "bounds": [290, 410, 531, 495]}, {"class": "ImageView", "visibility": "visible", "bounds": [236, 367, 347, 397]}, {"class": "ImageView", "visibility": "visible", "bounds": [470, 356, 601, 425]}, {"class": "ImageView", "visibility": "visible", "bounds": [53, 339, 234, 402]}, {"class": "ImageView", "visibility": "visible", "bounds": [749, 326, 767, 354]}, {"class": "ImageView", "visibility": "visible", "bounds": [589, 314, 613, 328]}, {"class": "ImageView", "visibility": "visible", "bounds": [813, 244, 915, 282]}, {"class": "ImageView", "visibility": "visible", "bounds": [528, 244, 635, 282]}, {"class": "ImageView", "visibility": "visible", "bounds": [444, 244, 525, 282]}, {"class": "ImageView", "visibility": "visible", "bounds": [163, 244, 283, 282]}, {"class": "ImageView", "visibility": "visible", "bounds": [76, 244, 160, 282]}, {"class": "ImageView", "visibility": "visible", "bounds": [44, 114, 102, 157]}, {"class": "ImageView", "visibility": "visible", "bounds": [1003, 107, 1025, 169]}, {"class": "ImageView", "visibility": "visible", "bounds": [308, 103, 563, 149]}, {"class": "ImageView", "visibility": "visible", "bounds": [185, 80, 285, 172]}, {"class": "ImageView", "visibility": "visible", "bounds": [983, 15, 1062, 51]}, {"class": "ImageView", "visibility": "visible", "bounds": [872, 9, 926, 54]}, {"class": "ImageView", "visibility": "visible", "bounds": [939, 8, 971, 54]}, {"class": "ImageView", "visibility": "visible", "bounds": [23, 8, 72, 53]}], "bounds": [0, 0, 1440, 2560]}}}