{"activity_name": "Users", "request_id": 3, "is_keyboard_deployed": false, "activity": {"added_fragments": ["1"], "active_fragments": ["1"], "root": {"class": "RelativeLayout", "visibility": "", "children": [{"class": "RelativeLayout", "visibility": "", "children": [{"class": "ImageView", "visibility": "visible", "bounds": [13, 13, 39, 39]}], "bounds": [818, 1831, 870, 1883]}, {"class": "RelativeLayout", "visibility": "", "children": [{"class": "ImageView", "visibility": "visible", "bounds": [14, 14, 44, 44]}], "bounds": [511, 1828, 569, 1886]}, {"class": "RelativeLayout", "visibility": "", "children": [{"class": "ImageView", "visibility": "visible", "bounds": [22, 20, 37, 38]}], "bounds": [211, 1828, 262, 1886]}, {"class": "RelativeLayout", "visibility": "", "children": [{"class": "ImageView", "visibility": "visible", "bounds": [50, 137, 67, 145]}, {"class": "ImageView", "visibility": "visible", "bounds": [17, 127, 35, 149]}], "bounds": [800, 1349, 1046, 1506]}, {"class": "RelativeLayout", "visibility": "", "children": [{"class": "ImageView", "visibility": "visible", "bounds": [8, 8, 36, 31]}], "bounds": [925, 243, 982, 282]}, {"class": "RelativeLayout", "visibility": "", "children": [{"class": "ImageView", "visibility": "visible", "bounds": [42, 39, 58, 53]}], "bounds": [185, 80, 285, 172]}, {"class": "RelativeLayout", "visibility": "", "children": [{"class": "ImageView", "visibility": "visible", "bounds": [8, 17, 31, 39]}], "bounds": [28, 8, 67, 55]}, {"class": "ImageView", "visibility": "visible", "bounds": [0, 1789, 1080, 1799]}, {"class": "ImageView", "visibility": "visible", "bounds": [36, 1615, 190, 1691]}, {"class": "ImageView", "visibility": "visible", "bounds": [800, 1583, 1046, 1740]}, {"class": "ImageView", "visibility": "visible", "bounds": [106, 1574, 161, 1605]}, {"class": "ImageView", "visibility": "visible", "bounds": [34, 1567, 105, 1601]}, {"class": "ImageView", "visibility": "visible", "bounds": [210, 1380, 491, 1464]}, {"class": "ImageView", "visibility": "visible", "bounds": [37, 1380, 215, 1457]}, {"class": "ImageView", "visibility": "visible", "bounds": [106, 1340, 161, 1371]}, {"class": "ImageView", "visibility": "visible", "bounds": [34, 1333, 105, 1367]}, {"class": "ImageView", "visibility": "visible", "bounds": [234, 1150, 362, 1223]}, {"class": "ImageView", "visibility": "visible", "bounds": [800, 1115, 1046, 1272]}, {"class": "ImageView", "visibility": "visible", "bounds": [106, 1106, 161, 1137]}, {"class": "ImageView", "visibility": "visible", "bounds": [34, 1099, 105, 1133]}, {"class": "ImageView", "visibility": "visible", "bounds": [800, 881, 1046, 1038]}, {"class": "ImageView", "visibility": "visible", "bounds": [106, 872, 161, 903]}, {"class": "ImageView", "visibility": "visible", "bounds": [34, 865, 105, 899]}, {"class": "ImageView", "visibility": "visible", "bounds": [892, 713, 908, 727]}, {"class": "ImageView", "visibility": "visible", "bounds": [800, 647, 1046, 804]}, {"class": "ImageView", "visibility": "visible", "bounds": [106, 638, 161, 669]}, {"class": "ImageView", "visibility": "visible", "bounds": [69, 632, 105, 663]}, {"class": "ImageView", "visibility": "visible", "bounds": [34, 631, 68, 665]}, {"class": "ImageView", "visibility": "visible", "bounds": [130, 483, 185, 514]}, {"class": "ImageView", "visibility": "visible", "bounds": [34, 476, 129, 510]}, {"class": "ImageView", "visibility": "visible", "bounds": [237, 330, 375, 373]}, {"class": "ImageView", "visibility": "visible", "bounds": [0, 305, 1080, 415]}, {"class": "ImageView", "visibility": "visible", "bounds": [820, 247, 907, 279]}, {"class": "ImageView", "visibility": "visible", "bounds": [529, 246, 622, 279]}, {"class": "ImageView", "visibility": "visible", "bounds": [456, 246, 528, 280]}, {"class": "ImageView", "visibility": "visible", "bounds": [44, 114, 102, 157]}, {"class": "ImageView", "visibility": "visible", "bounds": [1003, 107, 1025, 169]}, {"class": "ImageView", "visibility": "visible", "bounds": [308, 103, 563, 150]}, {"class": "ImageView", "visibility": "visible", "bounds": [994, 16, 1062, 48]}, {"class": "ImageView", "visibility": "visible", "bounds": [87, 12, 134, 51]}, {"class": "ImageView", "visibility": "visible", "bounds": [883, 9, 937, 54]}, {"class": "ImageView", "visibility": "visible", "bounds": [950, 8, 982, 54]}, {"class": "TextView", "visibility": "visible", "text": "TOP NEWS", "bounds": [95, 251, 264, 275]}, {"class": "TextView", "visibility": "visible", "text": "pressure to appoint envoy", "bounds": [41, 343, 480, 378]}, {"class": "TextView", "visibility": "visible", "text": "Australia's east coast battles rising COVID-19 cases", "bounds": [39, 531, 917, 566]}, {"class": "TextView", "visibility": "visible", "text": "U.S. Senate in rare Saturday session on $1", "bounds": [41, 678, 752, 712]}, {"class": "TextView", "visibility": "visible", "text": "trin infrastructure bill", "bounds": [40, 723, 407, 751]}, {"class": "TextView", "visibility": "visible", "text": "S.Korea July exports jump for ninth", "bounds": [40, 916, 634, 951]}, {"class": "TextView", "visibility": "visible", "text": "straight month, though pace slows", "bounds": [40, 958, 634, 993]}, {"class": "TextView", "visibility": "visible", "text": "Thousands protest against COVID-19", "bounds": [40, 1151, 668, 1186]}, {"class": "TextView", "visibility": "visible", "text": "health pass in France", "bounds": [41, 1192, 402, 1220]}, {"class": "TextView", "visibility": "visible", "text": "Discovery exploring takeover bid for UK's", "bounds": [42, 1385, 736, 1420]}, {"class": "TextView", "visibility": "visible", "text": "Channel 4 - The Telegraph", "bounds": [40, 1426, 487, 1453]}, {"class": "TextView", "visibility": "visible", "text": "Hungary nurses demand better pay to stem", "bounds": [42, 1622, 777, 1656]}], "bounds": [0, 0, 1440, 2560]}}}