{"activity_name": "Users", "request_id": 3, "is_keyboard_deployed": false, "activity": {"added_fragments": ["1"], "active_fragments": ["1"], "root": {"class": "RelativeLayout", "visibility": "", "children": [{"class": "RelativeLayout", "visibility": "", "children": [{"class": "ImageView", "visibility": "visible", "bounds": [13, 13, 39, 39]}], "bounds": [818, 1831, 870, 1883]}, {"class": "RelativeLayout", "visibility": "", "children": [{"class": "ImageView", "visibility": "visible", "bounds": [14, 14, 44, 44]}], "bounds": [511, 1828, 569, 1886]}, {"class": "RelativeLayout", "visibility": "", "children": [{"class": "ImageView", "visibility": "visible", "bounds": [22, 20, 37, 38]}], "bounds": [211, 1828, 262, 1886]}, {"class": "RelativeLayout", "visibility": "", "children": [{"class": "ImageView", "visibility": "visible", "bounds": [14, 14, 28, 28]}], "bounds": [204, 109, 258, 163]}, {"class": "RelativeLayout", "visibility": "", "children": [{"class": "ImageView", "visibility": "visible", "bounds": [34, 8, 63, 37]}], "bounds": [44, 96, 115, 157]}, {"class": "ImageView", "visibility": "visible", "bounds": [0, 1790, 1080, 1799]}, {"class": "ImageView", "visibility": "visible", "bounds": [22, 351, 125, 385]}, {"class": "ImageView", "visibility": "visible", "bounds": [171, 349, 295, 385]}, {"class": "ImageView", "visibility": "visible", "bounds": [128, 347, 170, 385]}, {"class": "ImageView", "visibility": "visible", "bounds": [150, 244, 278, 288]}, {"class": "ImageView", "visibility": "visible", "bounds": [23, 244, 145, 281]}, {"class": "ImageView", "visibility": "visible", "bounds": [0, 206, 1080, 215]}, {"class": "ImageView", "visibility": "visible", "bounds": [269, 178, 1062, 190]}, {"class": "ImageView", "visibility": "visible", "bounds": [292, 111, 456, 160]}, {"class": "ImageView", "visibility": "visible", "bounds": [964, 15, 1061, 51]}, {"class": "ImageView", "visibility": "visible", "bounds": [24, 12, 71, 51]}, {"class": "ImageView", "visibility": "visible", "bounds": [851, 9, 905, 54]}, {"class": "ImageView", "visibility": "visible", "bounds": [918, 8, 950, 54]}], "bounds": [0, 0, 1440, 2560]}}}