{"activity_name": "Users", "request_id": 3, "is_keyboard_deployed": false, "activity": {"added_fragments": ["1"], "active_fragments": ["1"], "root": {"class": "RelativeLayout", "visibility": "", "children": [{"class": "RelativeLayout", "visibility": "", "children": [{"class": "ImageView", "visibility": "visible", "bounds": [13, 13, 39, 39]}], "bounds": [818, 1831, 870, 1883]}, {"class": "RelativeLayout", "visibility": "", "children": [{"class": "ImageView", "visibility": "visible", "bounds": [14, 14, 44, 44]}], "bounds": [511, 1828, 569, 1886]}, {"class": "RelativeLayout", "visibility": "", "children": [{"class": "ImageView", "visibility": "visible", "bounds": [22, 20, 37, 38]}], "bounds": [211, 1828, 262, 1886]}, {"class": "RelativeLayout", "visibility": "", "children": [{"class": "ImageView", "visibility": "visible", "bounds": [248, 257, 260, 289]}, {"class": "ImageView", "visibility": "visible", "bounds": [267, 254, 274, 282]}], "bounds": [539, 651, 824, 1006]}, {"class": "RelativeLayout", "visibility": "", "children": [{"class": "ImageView", "visibility": "visible", "bounds": [150, 326, 159, 354]}, {"class": "ImageView", "visibility": "visible", "bounds": [92, 299, 142, 347]}, {"class": "ImageView", "visibility": "visible", "bounds": [165, 296, 207, 341]}], "bounds": [62, 593, 457, 956]}, {"class": "RelativeLayout", "visibility": "", "children": [{"class": "ImageView", "visibility": "visible", "bounds": [8, 17, 31, 39]}], "bounds": [154, 8, 193, 55]}, {"class": "RelativeLayout", "visibility": "", "children": [{"class": "ImageView", "visibility": "visible", "bounds": [23, 24, 39, 31]}], "bounds": [20, 8, 75, 55]}, {"class": "ImageView", "visibility": "visible", "bounds": [0, 1520, 1080, 1799]}, {"class": "ImageView", "visibility": "visible", "bounds": [900, 1256, 1024, 1295]}, {"class": "ImageView", "visibility": "visible", "bounds": [469, 1256, 593, 1294]}, {"class": "ImageView", "visibility": "visible", "bounds": [38, 1256, 162, 1295]}, {"class": "ImageView", "visibility": "visible", "bounds": [967, 1137, 1080, 1173]}, {"class": "ImageView", "visibility": "visible", "bounds": [811, 1137, 864, 1173]}, {"class": "ImageView", "visibility": "visible", "bounds": [779, 1137, 807, 1173]}, {"class": "ImageView", "visibility": "visible", "bounds": [902, 1031, 1080, 1067]}, {"class": "ImageView", "visibility": "visible", "bounds": [773, 1031, 855, 1067]}, {"class": "ImageView", "visibility": "visible", "bounds": [924, 669, 1080, 866]}, {"class": "ImageView", "visibility": "visible", "bounds": [0, 205, 1080, 214]}, {"class": "ImageView", "visibility": "visible", "bounds": [153, 95, 343, 178]}, {"class": "ImageView", "visibility": "visible", "bounds": [213, 12, 260, 51]}, {"class": "ImageView", "visibility": "visible", "bounds": [851, 9, 905, 54]}, {"class": "ImageView", "visibility": "visible", "bounds": [918, 8, 950, 54]}, {"class": "ImageView", "visibility": "visible", "bounds": [87, 8, 133, 55]}, {"class": "TextView", "visibility": "visible", "text": "11:51", "bounds": [968, 20, 1052, 46]}, {"class": "TextView", "visibility": "visible", "text": "= ebay", "bounds": [47, 113, 330, 195]}, {"class": "TextView", "visibility": "visible", "text": "Q", "bounds": [862, 107, 1048, 164]}, {"class": "TextView", "visibility": "visible", "text": "Sporting goods for all season long", "bounds": [44, 353, 934, 406]}, {"class": "TextView", "visibility": "visible", "text": "Score huge savings today.", "bounds": [43, 433, 466, 469]}, {"class": "TextView", "visibility": "visible", "text": "Shop Now >", "bounds": [43, 512, 305, 552]}, {"class": "TextView", "visibility": "visible", "text": "ODYSSEY TRIPLE TRACK CALLAWAY JAWS", "bounds": [44, 1035, 765, 1062]}, {"class": "TextView", "visibility": "visible", "text": "TEN SLANT PUTTER 35", "bounds": [43, 1088, 426, 1116]}, {"class": "TextView", "visibility": "visible", "text": "CHROME LOB WEDGE", "bounds": [475, 1088, 832, 1116]}, {"class": "TextView", "visibility": "visible", "text": "MAVRIK M", "bounds": [907, 1088, 1077, 1115]}, {"class": "TextView", "visibility": "visible", "text": "IN", "bounds": [45, 1142, 75, 1168]}, {"class": "TextView", "visibility": "visible", "text": "60\u00b0-10\u00b0 (BOUNCE)", "bounds": [475, 1141, 770, 1179]}, {"class": "TextView", "visibility": "visible", "text": "12\u00b0", "bounds": [907, 1141, 958, 1168]}, {"class": "TextView", "visibility": "visible", "text": "$177.99", "bounds": [44, 1201, 216, 1245]}, {"class": "TextView", "visibility": "visible", "text": "$100.79", "bounds": [475, 1201, 647, 1245]}, {"class": "TextView", "visibility": "visible", "text": "$219.99", "bounds": [906, 1201, 1078, 1245]}, {"class": "TextView", "visibility": "visible", "text": "-", "bounds": [169, 1274, 171, 1277]}, {"class": "TextView", "visibility": "visible", "text": "30%", "bounds": [183, 1264, 240, 1287]}, {"class": "TextView", "visibility": "visible", "text": "OFF", "bounds": [252, 1264, 307, 1287]}, {"class": "TextView", "visibility": "visible", "text": "-", "bounds": [600, 1274, 602, 1277]}, {"class": "TextView", "visibility": "visible", "text": "37%", "bounds": [614, 1264, 671, 1287]}, {"class": "TextView", "visibility": "visible", "text": "OFF", "bounds": [683, 1264, 738, 1287]}, {"class": "TextView", "visibility": "visible", "text": "-", "bounds": [1031, 1274, 1033, 1277]}, {"class": "TextView", "visibility": "visible", "text": "45", "bounds": [1045, 1264, 1079, 1287]}, {"class": "TextView", "visibility": "visible", "text": "Top tech for the taking", "bounds": [43, 1422, 628, 1471]}], "bounds": [0, 0, 1440, 2560]}}}