{"activity_name": "Users", "request_id": 3, "is_keyboard_deployed": false, "activity": {"added_fragments": ["1"], "active_fragments": ["1"], "root": {"class": "RelativeLayout", "visibility": "", "children": [{"class": "ImageView", "visibility": "visible", "bounds": [288, 781, 316, 800]}, {"class": "ImageView", "visibility": "visible", "bounds": [335, 780, 426, 800]}, {"class": "ImageView", "visibility": "visible", "bounds": [40, 773, 202, 800]}, {"class": "ImageView", "visibility": "visible", "bounds": [276, 769, 328, 800]}, {"class": "ImageView", "visibility": "visible", "bounds": [253, 748, 461, 800]}, {"class": "ImageView", "visibility": "visible", "bounds": [19, 748, 227, 800]}, {"class": "ImageView", "visibility": "visible", "bounds": [224, 694, 255, 717]}, {"class": "ImageView", "visibility": "visible", "bounds": [19, 520, 461, 615]}, {"class": "ImageView", "visibility": "visible", "bounds": [20, 456, 429, 505]}, {"class": "ImageView", "visibility": "visible", "bounds": [25, 419, 455, 431]}, {"class": "ImageView", "visibility": "visible", "bounds": [40, 394, 198, 408]}, {"class": "ImageView", "visibility": "visible", "bounds": [412, 385, 455, 416]}, {"class": "ImageView", "visibility": "visible", "bounds": [25, 311, 455, 355]}, {"class": "ImageView", "visibility": "visible", "bounds": [0, 185, 480, 199]}, {"class": "ImageView", "visibility": "visible", "bounds": [309, 145, 412, 169]}, {"class": "ImageView", "visibility": "visible", "bounds": [27, 62, 58, 94]}, {"class": "ImageView", "visibility": "visible", "bounds": [143, 58, 338, 98]}, {"class": "ImageView", "visibility": "visible", "bounds": [423, 6, 471, 31]}, {"class": "ImageView", "visibility": "visible", "bounds": [11, 5, 43, 31]}, {"class": "ImageView", "visibility": "visible", "bounds": [397, 2, 419, 32]}, {"class": "ImageView", "visibility": "visible", "bounds": [357, 2, 393, 32]}, {"class": "TextView", "visibility": "visible", "text": "EXISTING USER", "bounds": [51, 150, 191, 164]}, {"class": "TextView", "visibility": "visible", "text": "Sign in to score this great deal!", "bounds": [81, 233, 399, 255]}, {"class": "TextView", "visibility": "visible", "text": "Forgot password?", "bounds": [157, 640, 323, 659]}], "bounds": [0, 0, 1440, 2560]}}}