{"activity_name": "Users", "request_id": 3, "is_keyboard_deployed": false, "activity": {"added_fragments": ["1"], "active_fragments": ["1"], "root": {"class": "RelativeLayout", "visibility": "", "children": [{"class": "RelativeLayout", "visibility": "", "children": [{"class": "ImageView", "visibility": "visible", "bounds": [13, 13, 39, 39]}], "bounds": [818, 1831, 870, 1883]}, {"class": "RelativeLayout", "visibility": "", "children": [{"class": "ImageView", "visibility": "visible", "bounds": [14, 14, 44, 44]}], "bounds": [511, 1828, 569, 1886]}, {"class": "RelativeLayout", "visibility": "", "children": [{"class": "ImageView", "visibility": "visible", "bounds": [22, 20, 37, 38]}], "bounds": [211, 1828, 262, 1886]}, {"class": "RelativeLayout", "visibility": "", "children": [{"class": "ImageView", "visibility": "visible", "bounds": [8, 17, 31, 39]}], "bounds": [28, 8, 67, 55]}, {"class": "ImageView", "visibility": "visible", "bounds": [0, 1790, 1080, 1799]}, {"class": "ImageView", "visibility": "visible", "bounds": [447, 1482, 633, 1518]}, {"class": "ImageView", "visibility": "visible", "bounds": [858, 1446, 975, 1475]}, {"class": "ImageView", "visibility": "visible", "bounds": [748, 1446, 826, 1475]}, {"class": "ImageView", "visibility": "visible", "bounds": [155, 1446, 234, 1482]}, {"class": "ImageView", "visibility": "visible", "bounds": [830, 1445, 854, 1475]}, {"class": "ImageView", "visibility": "visible", "bounds": [549, 1438, 744, 1475]}, {"class": "ImageView", "visibility": "visible", "bounds": [501, 1438, 547, 1475]}, {"class": "ImageView", "visibility": "visible", "bounds": [436, 1438, 496, 1475]}, {"class": "ImageView", "visibility": "visible", "bounds": [105, 1438, 152, 1475]}, {"class": "ImageView", "visibility": "visible", "bounds": [238, 1437, 433, 1475]}, {"class": "ImageView", "visibility": "visible", "bounds": [566, 1252, 1043, 1409]}, {"class": "ImageView", "visibility": "visible", "bounds": [37, 1252, 513, 1409]}, {"class": "ImageView", "visibility": "visible", "bounds": [516, 1194, 564, 1227]}, {"class": "ImageView", "visibility": "visible", "bounds": [37, 1010, 1043, 1167]}, {"class": "ImageView", "visibility": "visible", "bounds": [204, 939, 363, 972]}, {"class": "ImageView", "visibility": "visible", "bounds": [93, 939, 203, 978]}, {"class": "ImageView", "visibility": "visible", "bounds": [769, 902, 829, 934]}, {"class": "ImageView", "visibility": "visible", "bounds": [38, 902, 90, 972]}, {"class": "ImageView", "visibility": "visible", "bounds": [631, 901, 728, 934]}, {"class": "ImageView", "visibility": "visible", "bounds": [731, 900, 767, 934]}, {"class": "ImageView", "visibility": "visible", "bounds": [542, 900, 630, 934]}, {"class": "ImageView", "visibility": "visible", "bounds": [342, 900, 436, 937]}, {"class": "ImageView", "visibility": "visible", "bounds": [82, 900, 197, 940]}, {"class": "ImageView", "visibility": "visible", "bounds": [37, 783, 94, 840]}, {"class": "ImageView", "visibility": "visible", "bounds": [48, 745, 1032, 757]}, {"class": "ImageView", "visibility": "visible", "bounds": [966, 689, 1031, 733]}, {"class": "ImageView", "visibility": "visible", "bounds": [73, 688, 284, 733]}, {"class": "ImageView", "visibility": "visible", "bounds": [48, 617, 1032, 629]}, {"class": "ImageView", "visibility": "visible", "bounds": [73, 560, 204, 605]}, {"class": "ImageView", "visibility": "visible", "bounds": [46, 489, 1034, 502]}, {"class": "ImageView", "visibility": "visible", "bounds": [356, 442, 478, 477]}, {"class": "ImageView", "visibility": "visible", "bounds": [73, 434, 169, 477]}, {"class": "ImageView", "visibility": "visible", "bounds": [268, 432, 348, 477]}, {"class": "ImageView", "visibility": "visible", "bounds": [176, 432, 258, 477]}, {"class": "ImageView", "visibility": "visible", "bounds": [0, 327, 1080, 341]}, {"class": "ImageView", "visibility": "visible", "bounds": [373, 106, 708, 168]}, {"class": "ImageView", "visibility": "visible", "bounds": [985, 16, 1004, 50]}, {"class": "ImageView", "visibility": "visible", "bounds": [964, 16, 983, 50]}, {"class": "ImageView", "visibility": "visible", "bounds": [1005, 15, 1062, 50]}, {"class": "ImageView", "visibility": "visible", "bounds": [87, 12, 134, 51]}, {"class": "ImageView", "visibility": "visible", "bounds": [851, 9, 905, 54]}, {"class": "ImageView", "visibility": "visible", "bounds": [918, 8, 950, 54]}, {"class": "TextView", "visibility": "visible", "text": "EXISTING USER", "bounds": [149, 261, 392, 286]}, {"class": "TextView", "visibility": "visible", "text": "NEW USER", "bounds": [728, 261, 895, 286]}, {"class": "TextView", "visibility": "visible", "text": "Yes, | want to save money by receiving personalized Groupon", "bounds": [111, 799, 974, 829]}, {"class": "TextView", "visibility": "visible", "text": "emails with awesome deals.", "bounds": [112, 836, 509, 860]}, {"class": "TextView", "visibility": "visible", "text": "By clicking an option below, | agree to the", "bounds": [45, 912, 625, 942]}, {"class": "TextView", "visibility": "visible", "text": "2 and have read", "bounds": [817, 905, 1032, 929]}], "bounds": [0, 0, 1440, 2560]}}}